snips_nlu_utils/__init__.py
snips_nlu_utils/__version__
snips_nlu_utils/string.py
snips_nlu_utils/token.py
snips_nlu_utils/utils.py
snips_nlu_utils/dylib/libsnips_nlu_utils_rs.so
snips_nlu_utils-0.9.1.dist-info/DESCRIPTION.rst
snips_nlu_utils-0.9.1.dist-info/METADATA
snips_nlu_utils-0.9.1.dist-info/RECORD
snips_nlu_utils-0.9.1.dist-info/WHEEL
snips_nlu_utils-0.9.1.dist-info/metadata.json
snips_nlu_utils-0.9.1.dist-info/top_level.txt
