Metadata-Version: 2.1
Name: snips-nlu-utils
Version: 0.9.1
Summary: Python wrapper of the snips-nlu-utils Rust crate
Home-page: UNKNOWN
Author: Adrien Ball
Author-email: adrien.ball@snips.ai
License: Apache 2.0
Platform: UNKNOWN
Classifier: Programming Language :: Python :: 2
Classifier: Programming Language :: Python :: 2.7
Classifier: Programming Language :: Python :: 3
Classifier: Programming Language :: Python :: 3.4
Classifier: Programming Language :: Python :: 3.5
Classifier: Programming Language :: Python :: 3.6
Classifier: Programming Language :: Python :: 3.7
Provides-Extra: test
